mcp_server_sparql/__init__.py
mcp_server_sparql/server.py
iflow_mcp_ekzhu_mcp_server_sparql-0.1.1.dist-info/METADATA
iflow_mcp_ekzhu_mcp_server_sparql-0.1.1.dist-info/WHEEL
iflow_mcp_ekzhu_mcp_server_sparql-0.1.1.dist-info/entry_points.txt
iflow_mcp_ekzhu_mcp_server_sparql-0.1.1.dist-info/licenses/LICENSE
iflow_mcp_ekzhu_mcp_server_sparql-0.1.1.dist-info/RECORD
