Metadata-Version: 2.4
Name: iflow-mcp_ekzhu_mcp-server-sparql
Version: 0.1.1
Summary: MCP server for querying SPARQL endpoint
Author-email: Eric Zhu <ekzhu@users.noreply.github.com>
License: MIT
License-File: LICENSE
Keywords: mcp,sparql
Classifier: Development Status :: 4 - Beta
Classifier: Intended Audience :: Developers
Classifier: License :: OSI Approved :: MIT License
Classifier: Programming Language :: Python :: 3
Classifier: Programming Language :: Python :: 3.10
Requires-Python: >=3.10
Requires-Dist: mcp>=1.6.0
Requires-Dist: sparqlwrapper>=2.0.0
